argvs.py
simpleargvs-1.1.0.dist-info/METADATA
simpleargvs-1.1.0.dist-info/WHEEL
simpleargvs-1.1.0.dist-info/top_level.txt
simpleargvs-1.1.0.dist-info/RECORD
