Metadata-Version: 2.4
Name: simpleargvs
Version: 1.1.0
Summary: A simpler way to use sys.argvs
Author-email: Bob Robertson <Coderdude123@proton.me>
License: MIT
Project-URL: Homepage, https://github.com/Jeff-web-sketch/argvs-lib-for-python/tree/main/argvs
Requires-Python: >=3.7
